libname/101917088.py
libname/__init__.py
Topsis_Harsh_101917088-2.0.1.dist-info/METADATA
Topsis_Harsh_101917088-2.0.1.dist-info/WHEEL
Topsis_Harsh_101917088-2.0.1.dist-info/top_level.txt
Topsis_Harsh_101917088-2.0.1.dist-info/RECORD
