Metadata-Version: 2.1
Name: Topsis-Harsh-101917088
Version: 2.0.1
Summary: Topsis Feature Choosing System
Home-page: UNKNOWN
Author: Harsh Kashyap
Author-email: hkashyap_be19@thapar.edu
License: UNKNOWN
Keywords: python,TOPSIS,Ranking
Platform: UNKNOWN
Classifier: Development Status :: 1 - Planning
Classifier: Intended Audience :: Developers
Classifier: Programming Language :: Python :: 3
Classifier: Operating System :: Unix
Classifier: Operating System :: MacOS :: MacOS X
Classifier: Operating System :: Microsoft :: Windows
Requires-Dist: numpy
Requires-Dist: pandas
Requires-Dist: sys
Requires-Dist: math
Requires-Dist: copy
